mu/__init__.py
mu/__main__.py
mu/app.py
mu/config.py
mu/i18n.py
mu/logic.py
mu/mu_debug.py
mu/settings.py
mu/virtual_environment.py
mu/contrib/__init__.py
mu/contrib/esptool.py
mu/contrib/microfs.py
mu/contrib/uflash.py
mu/debugger/client.py
mu/debugger/config.py
mu/debugger/runner.py
mu/debugger/utils.py
mu/interface/__init__.py
mu/interface/dialogs.py
mu/interface/editor.py
mu/interface/main.py
mu/interface/panes.py
mu/interface/themes.py
mu/interface/widgets.py
mu/interface/workers.py
mu/locale/de_DE/LC_MESSAGES/mu.mo
mu/locale/de_DE/LC_MESSAGES/mu.po
mu/locale/es/LC_MESSAGES/mu.mo
mu/locale/es/LC_MESSAGES/mu.po
mu/locale/fr/LC_MESSAGES/mu.mo
mu/locale/fr/LC_MESSAGES/mu.po
mu/locale/ja/LC_MESSAGES/mu.mo
mu/locale/ja/LC_MESSAGES/mu.po
mu/locale/pl/LC_MESSAGES/mu.mo
mu/locale/pl/LC_MESSAGES/mu.po
mu/locale/pt_BR/LC_MESSAGES/mu.mo
mu/locale/pt_BR/LC_MESSAGES/mu.po
mu/locale/pt_PT/LC_MESSAGES/mu.mo
mu/locale/pt_PT/LC_MESSAGES/mu.po
mu/locale/ru_RU/LC_MESSAGES/mu.mo
mu/locale/ru_RU/LC_MESSAGES/mu.po
mu/locale/sk_SK/LC_MESSAGES/mu.mo
mu/locale/sk_SK/LC_MESSAGES/mu.po
mu/locale/sv/LC_MESSAGES/mu.mo
mu/locale/sv/LC_MESSAGES/mu.po
mu/locale/vi/LC_MESSAGES/mu.mo
mu/locale/vi/LC_MESSAGES/mu.po
mu/locale/zh_CN/LC_MESSAGES/mu.mo
mu/locale/zh_CN/LC_MESSAGES/mu.po
mu/modes/__init__.py
mu/modes/base.py
mu/modes/circuitpython.py
mu/modes/debugger.py
mu/modes/esp.py
mu/modes/lego.py
mu/modes/microbit.py
mu/modes/pico.py
mu/modes/pyboard.py
mu/modes/pygamezero.py
mu/modes/python3.py
mu/modes/snek.py
mu/modes/web.py
mu/modes/api/__init__.py
mu/modes/api/adafruit.py
mu/modes/api/esp.py
mu/modes/api/flask.py
mu/modes/api/lego.py
mu/modes/api/microbit.py
mu/modes/api/pi.py
mu/modes/api/pyboard.py
mu/modes/api/pygamezero.py
mu/modes/api/python3.py
mu/modes/api/shared.py
mu/modes/api/snek.py
mu/resources/__init__.py
mu/resources/css/contrast.css
mu/resources/css/day.css
mu/resources/css/night.css
mu/resources/fonts/LICENSE.txt
mu/resources/fonts/SourceCodePro-Bold.otf
mu_editor-1.2.0.dist-info/AUTHORS.rst
mu_editor-1.2.0.dist-info/LICENSE
mu_editor-1.2.0.dist-info/METADATA
mu_editor-1.2.0.dist-info/WHEEL
mu_editor-1.2.0.dist-info/entry_points.txt
mu_editor-1.2.0.dist-info/top_level.txt
mu_editor-1.2.0.dist-info/RECORD
