Metadata-Version: 2.1
Name: mu-editor
Version: 1.2.0
Summary: A simple Python editor for beginner programmers.
Home-page: https://github.com/mu-editor/mu
Author: Nicholas H.Tollervey
Author-email: ntoll@ntoll.org
License: GPL3
Platform: UNKNOWN
Classifier: Development Status :: 5 - Production/Stable
Classifier: Environment :: Win32 (MS Windows)
Classifier: Environment :: X11 Applications :: Qt
Classifier: Environment :: MacOS X
Classifier: Intended Audience :: Developers
Classifier: Intended Audience :: Education
Classifier: Intended Audience :: End Users/Desktop
Classifier: License :: OSI Approved :: GNU General Public License v3 (GPLv3)
Classifier: Operating System :: POSIX
Classifier: Operating System :: MacOS :: MacOS X
Classifier: Operating System :: Microsoft :: Windows
Classifier: Programming Language :: Python :: 3 :: Only
Classifier: Programming Language :: Python :: 3.5
Classifier: Programming Language :: Python :: 3.6
Classifier: Programming Language :: Python :: 3.7
Classifier: Programming Language :: Python :: 3.8
Classifier: Topic :: Education
Classifier: Topic :: Games/Entertainment
Classifier: Topic :: Software Development
Classifier: Topic :: Software Development :: Debuggers
Classifier: Topic :: Software Development :: Embedded Systems
Classifier: Topic :: Text Editors
Classifier: Topic :: Text Editors :: Integrated Development Environments (IDE)
Requires-Python: >=3.5,<3.9
License-File: LICENSE
License-File: AUTHORS.rst
Requires-Dist: jupyter-client (<6.2,>=4.1)
Requires-Dist: ipykernel (<6,>=4.1)
Requires-Dist: ipython-genutils (>=0.2.0)
Requires-Dist: qtconsole (==4.7.7)
Requires-Dist: adafruit-board-toolkit (~=1.1)
Requires-Dist: pyserial (~=3.5)
Requires-Dist: nudatus (>=0.0.3)
Requires-Dist: flake8 (>=3.8.3)
Requires-Dist: click (<=8.0.4)
Requires-Dist: platformdirs (<3.0.0,>=2.0.0)
Requires-Dist: semver (>=2.8.0)
Requires-Dist: virtualenv (>=20.0.0)
Requires-Dist: wheel
Requires-Dist: requests (>=2.0.0)
Requires-Dist: PyQt5 (==5.13.2) ; "arm" not in platform_machine and "aarch" not in platform_machine
Requires-Dist: QScintilla (==2.11.3) ; "arm" not in platform_machine and "aarch" not in platform_machine
Requires-Dist: PyQtChart (==5.13.1) ; "arm" not in platform_machine and "aarch" not in platform_machine
Requires-Dist: black (<22.1.0,>=19.10b0) ; python_version > "3.5"
Requires-Dist: pywin32 ; sys_platform == "win32"
Provides-Extra: all
Requires-Dist: pytest-timeout ; extra == 'all'
Requires-Dist: twine ; extra == 'all'
Requires-Dist: pytest-cov ; extra == 'all'
Requires-Dist: scrapy ; extra == 'all'
Requires-Dist: pytest-faulthandler ; extra == 'all'
Requires-Dist: sphinx ; extra == 'all'
Requires-Dist: wheel ; extra == 'all'
Requires-Dist: coverage ; extra == 'all'
Requires-Dist: requests ; extra == 'all'
Requires-Dist: pytest (>=4.6) ; extra == 'all'
Requires-Dist: pytest-random-order (>=1.0.0) ; extra == 'all'
Requires-Dist: beautifulsoup4 ; extra == 'all'
Requires-Dist: babel ; extra == 'all'
Provides-Extra: dev
Requires-Dist: pytest (>=4.6) ; extra == 'dev'
Requires-Dist: pytest-cov ; extra == 'dev'
Requires-Dist: pytest-random-order (>=1.0.0) ; extra == 'dev'
Requires-Dist: pytest-faulthandler ; extra == 'dev'
Requires-Dist: pytest-timeout ; extra == 'dev'
Requires-Dist: coverage ; extra == 'dev'
Requires-Dist: sphinx ; extra == 'dev'
Requires-Dist: wheel ; extra == 'dev'
Requires-Dist: twine ; extra == 'dev'
Requires-Dist: babel ; extra == 'dev'
Provides-Extra: docs
Requires-Dist: sphinx ; extra == 'docs'
Provides-Extra: i18n
Requires-Dist: babel ; extra == 'i18n'
Provides-Extra: package
Requires-Dist: wheel ; extra == 'package'
Requires-Dist: twine ; extra == 'package'
Provides-Extra: tests
Requires-Dist: pytest (>=4.6) ; extra == 'tests'
Requires-Dist: pytest-cov ; extra == 'tests'
Requires-Dist: pytest-random-order (>=1.0.0) ; extra == 'tests'
Requires-Dist: pytest-faulthandler ; extra == 'tests'
Requires-Dist: pytest-timeout ; extra == 'tests'
Requires-Dist: coverage ; extra == 'tests'
Provides-Extra: utils
Requires-Dist: scrapy ; extra == 'utils'
Requires-Dist: beautifulsoup4 ; extra == 'utils'
Requires-Dist: requests ; extra == 'utils'
